boursobank_scraper/__init__.py
boursobank_scraper/__main__.py
boursobank_scraper/account.py
boursobank_scraper/bourso_scraper.py
boursobank_scraper/button.py
boursobank_scraper/config.py
boursobank_scraper/models.py
boursobank_scraper/py.typed
boursobank_scraper/reference_buttons.py
boursobank_scraper-0.5.0.dist-info/WHEEL
boursobank_scraper-0.5.0.dist-info/entry_points.txt
boursobank_scraper-0.5.0.dist-info/METADATA
boursobank_scraper-0.5.0.dist-info/RECORD
