Metadata-Version: 2.3
Name: boursobank-scraper
Version: 0.5.0
Summary: Outil pour récupérer les données de transaction depuis le site de BoursoBank
Author: glops
Author-email: glops <skylvl@gmail.com>
Requires-Dist: msgspec>=0.19.0
Requires-Dist: playwright>=1.55.0
Requires-Dist: pyyaml>=6.0.3
Requires-Python: >=3.13
